{
  "generated_at": "2026-04-25T13:41:00.700Z",
  "matches": [
    {
      "wallet": "0x0000000f2eb9f69274678c76222b35eec7588a65",
      "address": "0x12b004719fb632f1e7c010c6f5d6009fb4258442",
      "kind": "ybs",
      "match": {
        "name": "LIUSD-1W",
        "protocol": "infinifi",
        "apr": "6.56%",
        "aprValue": 6.55909,
        "apy_1d": 6.55909,
        "apy_7d": 6.4115883333333334,
        "apy_30d": 5.99239,
        "chain": "Ethereum",
        "tvl": "$6M",
        "tvlNum": 5834510,
        "source": "defillama",
        "addresses": [
          "0x12b004719fb632f1e7c010c6f5d6009fb4258442"
        ],
        "aliases": [
          "liUSD-1W"
        ]
      }
    },
    {
      "wallet": "0x815f5bb257e88b67216a344c7c83a3ea4ee74748",
      "address": "0x88887be419578051ff9f4eb6c858a951921d8888",
      "kind": "ybs",
      "match": {
        "name": "stcUSD",
        "protocol": "cap",
        "apr": "5.69%",
        "aprValue": 5.68776,
        "apy_1d": 5.68776,
        "apy_7d": 6.352183125,
        "apy_30d": 5.66309,
        "chain": "Ethereum",
        "tvl": "$103M",
        "tvlNum": 103088210,
        "source": "defillama",
        "addresses": [
          "0x88887be419578051ff9f4eb6c858a951921d8888"
        ],
        "aliases": [
          "stcUSD"
        ]
      }
    },
    {
      "wallet": "0x502d222e8e4daef69032f55f0c1a999effd78fb3",
      "address": "0x9d39a5de30e57443bff2a8307a4256c8797a3497",
      "kind": "ybs",
      "match": {
        "name": "sUSDe",
        "protocol": "ethena-usde",
        "apr": "5.28%",
        "aprValue": 5.2837,
        "apy_1d": 5.2837,
        "apy_7d": 4.7284203125,
        "apy_30d": 3.8214,
        "chain": "Ethereum",
        "tvl": "$2172M",
        "tvlNum": 2172262403,
        "source": "defillama",
        "addresses": [
          "0x9D39A5DE30e57443BfF2A8307A4256c8797A3497"
        ],
        "aliases": [
          "sUSDe"
        ]
      }
    },
    {
      "wallet": "0x289c204b35859bfb924b9c0759a4fe80f610671c",
      "address": "0xdbdc1ef57537e34680b898e1febd3d68c7389bcb",
      "kind": "ybs",
      "match": {
        "name": "siUSD",
        "protocol": "infinifi",
        "apr": "6.03%",
        "aprValue": 6.03418,
        "apy_1d": 6.03418,
        "apy_7d": 6.291381875,
        "apy_30d": 5.79579,
        "chain": "Ethereum",
        "tvl": "$40M",
        "tvlNum": 40156364,
        "source": "defillama",
        "addresses": [
          "0xdbdc1ef57537e34680b898e1febd3d68c7389bcb"
        ],
        "aliases": [
          "siUSD"
        ]
      }
    },
    {
      "wallet": "0xd1a1c248b253f1fc60eacd90777b9a63f8c8c1bc",
      "address": "0x66bcf6151d5558afb47c38b20663589843156078",
      "kind": "ybs",
      "match": {
        "name": "LIUSD-4W",
        "protocol": "infinifi",
        "apr": "7.92%",
        "aprValue": 7.92163,
        "apy_1d": 7.92163,
        "apy_7d": 7.742451666666667,
        "apy_30d": 7.23355,
        "chain": "Ethereum",
        "tvl": "$11M",
        "tvlNum": 10872697,
        "source": "defillama",
        "addresses": [
          "0x66bcf6151d5558afb47c38b20663589843156078"
        ],
        "aliases": [
          "liUSD-4W"
        ]
      }
    },
    {
      "wallet": "0xbeef123217647014429b7670329782e210884e89",
      "address": "0xa3931d71877c0e7a3148cb7eb4463524fec27fbd",
      "kind": "ybs",
      "match": {
        "name": "sUSDS",
        "protocol": "sky-lending",
        "apr": "3.65%",
        "aprValue": 3.65,
        "apy_1d": 3.65,
        "apy_7d": 3.69375,
        "apy_30d": 3.74043,
        "chain": "Ethereum",
        "tvl": "$5304M",
        "tvlNum": 5303976942,
        "source": "defillama",
        "addresses": [
          "0xa3931d71877c0e7a3148cb7eb4463524fec27fbd"
        ],
        "aliases": [
          "sUSDS"
        ]
      }
    },
    {
      "wallet": "0x9f1a1479191af103ff82fead23e950b6b3b2bd1a",
      "address": "0xa3931d71877c0e7a3148cb7eb4463524fec27fbd",
      "kind": "ybs",
      "match": {
        "name": "sUSDS",
        "protocol": "sky-lending",
        "apr": "3.65%",
        "aprValue": 3.65,
        "apy_1d": 3.65,
        "apy_7d": 3.69375,
        "apy_30d": 3.74043,
        "chain": "Ethereum",
        "tvl": "$5304M",
        "tvlNum": 5303976942,
        "source": "defillama",
        "addresses": [
          "0xa3931d71877c0e7a3148cb7eb4463524fec27fbd"
        ],
        "aliases": [
          "sUSDS"
        ]
      }
    },
    {
      "wallet": "0x70ac345ab736ce145e0d4b5deced7a8bcb0e4033",
      "address": "0x80ac24aa929eaf5013f6436cda2a7ba190f5cc0b",
      "kind": "ybs",
      "match": {
        "name": "syrupUSDC",
        "protocol": "jupiter-lend",
        "apr": "5.11%",
        "aprValue": 5.10573,
        "apy_1d": 5.10573,
        "apy_7d": 4.854035,
        "apy_30d": 4.54106,
        "chain": "Solana",
        "tvl": "$2M",
        "tvlNum": 2370281,
        "source": "defillama",
        "addresses": [
          "0x80ac24aa929eaf5013f6436cda2a7ba190f5cc0b"
        ],
        "aliases": [
          "syrupUSDC"
        ]
      }
    },
    {
      "wallet": "0xd6c757043e7d59088969b188923c62fa960afe9b",
      "address": "0xad55aebc9b8c03fc43cd9f62260391c13c23e7c0",
      "kind": "ybs",
      "match": {
        "name": "cUSDO",
        "protocol": "usdo",
        "apr": "3.53%",
        "aprValue": 3.52862,
        "apy_1d": 3.52862,
        "apy_7d": 3.9762771875,
        "apy_30d": 3.89378,
        "chain": "Ethereum",
        "tvl": "$1M",
        "tvlNum": 1407605,
        "source": "defillama",
        "addresses": [
          "0xad55aebc9b8c03fc43cd9f62260391c13c23e7c0"
        ],
        "aliases": [
          "cUSDO"
        ]
      }
    },
    {
      "wallet": "0x9ea38e09f41a9de53972a68268ba0dcc6d2fadf8",
      "address": "0x9d39a5de30e57443bff2a8307a4256c8797a3497",
      "kind": "ybs",
      "match": {
        "name": "sUSDe",
        "protocol": "ethena-usde",
        "apr": "5.28%",
        "aprValue": 5.2837,
        "apy_1d": 5.2837,
        "apy_7d": 4.7284203125,
        "apy_30d": 3.8214,
        "chain": "Ethereum",
        "tvl": "$2172M",
        "tvlNum": 2172262403,
        "source": "defillama",
        "addresses": [
          "0x9D39A5DE30e57443BfF2A8307A4256c8797A3497"
        ],
        "aliases": [
          "sUSDe"
        ]
      }
    },
    {
      "wallet": "0x295f67fdb21255a3db82964445628a706fbe689e",
      "address": "0x12b004719fb632f1e7c010c6f5d6009fb4258442",
      "kind": "ybs",
      "match": {
        "name": "LIUSD-1W",
        "protocol": "infinifi",
        "apr": "6.56%",
        "aprValue": 6.55909,
        "apy_1d": 6.55909,
        "apy_7d": 6.4115883333333334,
        "apy_30d": 5.99239,
        "chain": "Ethereum",
        "tvl": "$6M",
        "tvlNum": 5834510,
        "source": "defillama",
        "addresses": [
          "0x12b004719fb632f1e7c010c6f5d6009fb4258442"
        ],
        "aliases": [
          "liUSD-1W"
        ]
      }
    },
    {
      "wallet": "0x295f67fdb21255a3db82964445628a706fbe689e",
      "address": "0x5086bf358635b81d8c47c66d1c8b9e567db70c72",
      "kind": "ybs",
      "match": {
        "name": "reUSD",
        "protocol": "re-protocol",
        "apr": "9.11%",
        "aprValue": 9.11419,
        "apy_1d": 9.11419,
        "apy_7d": 9.0647521875,
        "apy_30d": 8.31555,
        "chain": "Ethereum",
        "tvl": "$7M",
        "tvlNum": 6716591,
        "source": "defillama",
        "addresses": [
          "0x5086bf358635b81d8c47c66d1c8b9e567db70c72"
        ],
        "aliases": [
          "reUSD"
        ]
      }
    },
    {
      "wallet": "0x295f67fdb21255a3db82964445628a706fbe689e",
      "address": "0x66bcf6151d5558afb47c38b20663589843156078",
      "kind": "ybs",
      "match": {
        "name": "LIUSD-4W",
        "protocol": "infinifi",
        "apr": "7.92%",
        "aprValue": 7.92163,
        "apy_1d": 7.92163,
        "apy_7d": 7.742451666666667,
        "apy_30d": 7.23355,
        "chain": "Ethereum",
        "tvl": "$11M",
        "tvlNum": 10872697,
        "source": "defillama",
        "addresses": [
          "0x66bcf6151d5558afb47c38b20663589843156078"
        ],
        "aliases": [
          "liUSD-4W"
        ]
      }
    },
    {
      "wallet": "0x295f67fdb21255a3db82964445628a706fbe689e",
      "address": "0x9d39a5de30e57443bff2a8307a4256c8797a3497",
      "kind": "ybs",
      "match": {
        "name": "sUSDe",
        "protocol": "ethena-usde",
        "apr": "5.28%",
        "aprValue": 5.2837,
        "apy_1d": 5.2837,
        "apy_7d": 4.7284203125,
        "apy_30d": 3.8214,
        "chain": "Ethereum",
        "tvl": "$2172M",
        "tvlNum": 2172262403,
        "source": "defillama",
        "addresses": [
          "0x9D39A5DE30e57443BfF2A8307A4256c8797A3497"
        ],
        "aliases": [
          "sUSDe"
        ]
      }
    },
    {
      "wallet": "0x295f67fdb21255a3db82964445628a706fbe689e",
      "address": "0xdbdc1ef57537e34680b898e1febd3d68c7389bcb",
      "kind": "ybs",
      "match": {
        "name": "siUSD",
        "protocol": "infinifi",
        "apr": "6.03%",
        "aprValue": 6.03418,
        "apy_1d": 6.03418,
        "apy_7d": 6.291381875,
        "apy_30d": 5.79579,
        "chain": "Ethereum",
        "tvl": "$40M",
        "tvlNum": 40156364,
        "source": "defillama",
        "addresses": [
          "0xdbdc1ef57537e34680b898e1febd3d68c7389bcb"
        ],
        "aliases": [
          "siUSD"
        ]
      }
    },
    {
      "wallet": "0x295f67fdb21255a3db82964445628a706fbe689e",
      "address": "0xf68b95b7e851170c0e5123a3249dd1ca46215085",
      "kind": "ybs",
      "match": {
        "name": "LIUSD-8W",
        "protocol": "infinifi",
        "apr": "8.95%",
        "aprValue": 8.95495,
        "apy_1d": 8.95495,
        "apy_7d": 8.751515,
        "apy_30d": 8.174,
        "chain": "Ethereum",
        "tvl": "$7M",
        "tvlNum": 7412905,
        "source": "defillama",
        "addresses": [
          "0xf68b95b7e851170c0e5123a3249dd1ca46215085"
        ],
        "aliases": [
          "liUSD-8W"
        ]
      }
    },
    {
      "wallet": "0x5c454f5526e41fbe917b63475cd8ca7e4631b147",
      "address": "0x9d39a5de30e57443bff2a8307a4256c8797a3497",
      "kind": "ybs",
      "match": {
        "name": "sUSDe",
        "protocol": "ethena-usde",
        "apr": "5.28%",
        "aprValue": 5.2837,
        "apy_1d": 5.2837,
        "apy_7d": 4.7284203125,
        "apy_30d": 3.8214,
        "chain": "Ethereum",
        "tvl": "$2172M",
        "tvlNum": 2172262403,
        "source": "defillama",
        "addresses": [
          "0x9D39A5DE30e57443BfF2A8307A4256c8797A3497"
        ],
        "aliases": [
          "sUSDe"
        ]
      }
    },
    {
      "wallet": "0xd4374008c88321eb2e59abd311156c44b25831e9",
      "address": "0x9d39a5de30e57443bff2a8307a4256c8797a3497",
      "kind": "ybs",
      "match": {
        "name": "sUSDe",
        "protocol": "ethena-usde",
        "apr": "5.28%",
        "aprValue": 5.2837,
        "apy_1d": 5.2837,
        "apy_7d": 4.7284203125,
        "apy_30d": 3.8214,
        "chain": "Ethereum",
        "tvl": "$2172M",
        "tvlNum": 2172262403,
        "source": "defillama",
        "addresses": [
          "0x9D39A5DE30e57443BfF2A8307A4256c8797A3497"
        ],
        "aliases": [
          "sUSDe"
        ]
      }
    }
  ]
}