{
  "generated_at": "2026-04-25T11:16:27.442Z",
  "summary": {
    "total_positions": 144,
    "unresolved_fallback_positions": 0,
    "unresolved_fallback_usd": 0
  },
  "by_source_type": {
    "scanner": {
      "positions": 106,
      "net_usd": 268163507.47806254
    },
    "fallback": {
      "positions": 38,
      "net_usd": 162351782.43925786
    }
  },
  "by_protocol": {
    "aave": {
      "positions": 19,
      "net_usd": 73727616.9744657
    },
    "morpho": {
      "positions": 55,
      "net_usd": 144630494.44495794
    },
    "pendle": {
      "positions": 7,
      "net_usd": 3905703.170484191
    },
    "wallet-held": {
      "positions": 11,
      "net_usd": 26767547.282870125
    },
    "ybs": {
      "positions": 6,
      "net_usd": 86251189.35370934
    },
    "spark": {
      "positions": 3,
      "net_usd": 38349.78628861135
    },
    "spark-savings-legacy": {
      "positions": 1,
      "net_usd": 0.06928249169986722
    },
    "euler": {
      "positions": 21,
      "net_usd": 43092918.47170426
    },
    "fluid": {
      "positions": 4,
      "net_usd": 2806774.4164503915
    },
    "curve": {
      "positions": 2,
      "net_usd": 2957897.1620512903
    },
    "ethena": {
      "positions": 1,
      "net_usd": 9945536.074540157
    },
    "yuzumoney": {
      "positions": 1,
      "net_usd": 694603.236950766
    },
    "curvance": {
      "positions": 4,
      "net_usd": 6513505.985432149
    },
    "gearbox": {
      "positions": 2,
      "net_usd": 1149421.47003995
    },
    "dolomite": {
      "positions": 1,
      "net_usd": 1267425.8922384768
    },
    "traderjoe": {
      "positions": 1,
      "net_usd": 833807.3434088461
    },
    "ethstrat": {
      "positions": 1,
      "net_usd": 721731.4237929836
    },
    "bsc_venusflux": {
      "positions": 1,
      "net_usd": 1053394.7400384862
    },
    "vault-probed": {
      "positions": 1,
      "net_usd": 799907.5691392253
    },
    "yo-protocol": {
      "positions": 2,
      "net_usd": 23357465.049474943
    }
  },
  "by_protocol_source": [
    {
      "protocol": "morpho",
      "source_type": "scanner",
      "positions": 55,
      "net_usd": 144630494.44495794,
      "normalization_status": "canonical"
    },
    {
      "protocol": "ybs",
      "source_type": "fallback",
      "positions": 6,
      "net_usd": 86251189.35370934,
      "normalization_status": "partial"
    },
    {
      "protocol": "aave",
      "source_type": "scanner",
      "positions": 19,
      "net_usd": 73727616.9744657,
      "normalization_status": "canonical"
    },
    {
      "protocol": "euler",
      "source_type": "scanner",
      "positions": 21,
      "net_usd": 43092918.47170426,
      "normalization_status": "canonical"
    },
    {
      "protocol": "wallet-held",
      "source_type": "fallback",
      "positions": 11,
      "net_usd": 26767547.282870125,
      "normalization_status": "partial"
    },
    {
      "protocol": "yo-protocol",
      "source_type": "fallback",
      "positions": 2,
      "net_usd": 23357465.049474943,
      "normalization_status": "partial"
    },
    {
      "protocol": "ethena",
      "source_type": "fallback",
      "positions": 1,
      "net_usd": 9945536.074540157,
      "normalization_status": "partial"
    },
    {
      "protocol": "curvance",
      "source_type": "fallback",
      "positions": 4,
      "net_usd": 6513505.985432149,
      "normalization_status": "partial"
    },
    {
      "protocol": "pendle",
      "source_type": "scanner",
      "positions": 7,
      "net_usd": 3905703.170484191,
      "normalization_status": "canonical"
    },
    {
      "protocol": "curve",
      "source_type": "fallback",
      "positions": 2,
      "net_usd": 2957897.1620512903,
      "normalization_status": "partial"
    },
    {
      "protocol": "fluid",
      "source_type": "scanner",
      "positions": 4,
      "net_usd": 2806774.4164503915,
      "normalization_status": "canonical"
    },
    {
      "protocol": "dolomite",
      "source_type": "fallback",
      "positions": 1,
      "net_usd": 1267425.8922384768,
      "normalization_status": "partial"
    },
    {
      "protocol": "gearbox",
      "source_type": "fallback",
      "positions": 2,
      "net_usd": 1149421.47003995,
      "normalization_status": "partial"
    },
    {
      "protocol": "bsc_venusflux",
      "source_type": "fallback",
      "positions": 1,
      "net_usd": 1053394.7400384862,
      "normalization_status": "partial"
    },
    {
      "protocol": "traderjoe",
      "source_type": "fallback",
      "positions": 1,
      "net_usd": 833807.3434088461,
      "normalization_status": "partial"
    },
    {
      "protocol": "vault-probed",
      "source_type": "fallback",
      "positions": 1,
      "net_usd": 799907.5691392253,
      "normalization_status": "partial"
    },
    {
      "protocol": "ethstrat",
      "source_type": "fallback",
      "positions": 1,
      "net_usd": 721731.4237929836,
      "normalization_status": "partial"
    },
    {
      "protocol": "yuzumoney",
      "source_type": "fallback",
      "positions": 1,
      "net_usd": 694603.236950766,
      "normalization_status": "partial"
    },
    {
      "protocol": "spark",
      "source_type": "fallback",
      "positions": 3,
      "net_usd": 38349.78628861135,
      "normalization_status": "partial"
    },
    {
      "protocol": "spark-savings-legacy",
      "source_type": "fallback",
      "positions": 1,
      "net_usd": 0.06928249169986722,
      "normalization_status": "partial"
    }
  ]
}